rcute_cozmars/__init__.py
rcute_cozmars/animation.py
rcute_cozmars/aruco.py
rcute_cozmars/button.py
rcute_cozmars/buzzer.py
rcute_cozmars/camera.py
rcute_cozmars/cube.py
rcute_cozmars/cube_animation.py
rcute_cozmars/cube_charge_animation.py
rcute_cozmars/env.py
rcute_cozmars/eye_animation.py
rcute_cozmars/head.py
rcute_cozmars/infrared.py
rcute_cozmars/led.py
rcute_cozmars/lift.py
rcute_cozmars/microphone.py
rcute_cozmars/motor.py
rcute_cozmars/robot.py
rcute_cozmars/screen.py
rcute_cozmars/sonar.py
rcute_cozmars/sound_mixin.py
rcute_cozmars/speaker.py
rcute_cozmars/util.py
rcute_cozmars/version.py
rcute_cozmars/resources/msyh.ttc
rcute_cozmars-2.0.0.dist-info/DESCRIPTION.rst
rcute_cozmars-2.0.0.dist-info/METADATA
rcute_cozmars-2.0.0.dist-info/RECORD
rcute_cozmars-2.0.0.dist-info/WHEEL
rcute_cozmars-2.0.0.dist-info/metadata.json
rcute_cozmars-2.0.0.dist-info/top_level.txt
