Metadata-Version: 2.0
Name: rcute-cozmars
Version: 2.0.0
Summary: Python SDK for Cozmars, the 3d printable educational robot.
Home-page: https://github.com/hyansuper/rcute-cozmars
Author: Huang Yan
Author-email: hyansuper@foxmail.com
License: MIT
Platform: UNKNOWN
Classifier: Programming Language :: Python :: 3.7
Classifier: License :: OSI Approved :: MIT License
Classifier: Operating System :: OS Independent
Requires-Dist: Pillow
Requires-Dist: aiohttp
Requires-Dist: gpiozero
Requires-Dist: librosa
Requires-Dist: numpy
Requires-Dist: opencv-contrib-python
Requires-Dist: opencv-python
Requires-Dist: pydub
Requires-Dist: soundfile
Requires-Dist: websockets
Requires-Dist: wsmprpc (>=1.1.1)
